spectradb/__init__.py
spectradb/main.py
spectradb/types.py
spectradb/dataloaders/__init__.py
spectradb/dataloaders/base.py
spectradb/dataloaders/dataloader.py
spectradb/utils/__init__.py
spectradb/utils/decorators.py
spectradb/utils/utils.py
spectradb-1.0.6.dist-info/licenses/LICENSE
spectradb-1.0.6.dist-info/METADATA
spectradb-1.0.6.dist-info/WHEEL
spectradb-1.0.6.dist-info/top_level.txt
spectradb-1.0.6.dist-info/RECORD
