Metadata-Version: 2.4
Name: spectradb
Version: 1.0.6
Summary: "A Lightweight Spectroscopic Data Manager"
Home-page: https://github.com/acmoudleysa/SpectraDB
Author: Amulya Baniya
Author-email: ronaldoamulya@gmail.com
Project-URL: Bug reports, https://github.com/acmoudleysa/SpectraDB/issues
Project-URL: Source, https://github.com/acmoudleysa/SpectraDB
Keywords: spectradb ftir fluorescence 2dfluorescence nmr chemometrics
Classifier: Programming Language :: Python :: 3.11
Classifier: Programming Language :: Python :: 3.10
Classifier: Programming Language :: Python :: 3.9
Classifier: Operating System :: OS Independent
Requires-Python: <4,>=3.9
License-File: LICENSE
Requires-Dist: numpy
Requires-Dist: pandas
Requires-Dist: plotly
Requires-Dist: plotly-express
Dynamic: license-file
